solderx/__init__.py
solderx/cli.py
solderx/fuse_file.py
solderx/fuse_folder.py
solderx/fuse_scan.py
solderx/utils.py
solderx-0.1.1.dist-info/licenses/LICENSE
solderx-0.1.1.dist-info/METADATA
solderx-0.1.1.dist-info/WHEEL
solderx-0.1.1.dist-info/entry_points.txt
solderx-0.1.1.dist-info/top_level.txt
solderx-0.1.1.dist-info/RECORD
