Metadata-Version: 2.4
Name: solderx
Version: 0.1.1
Summary: ⚡️ SolderX – Melt Imports. Solder Solidity. Flatten Everything 🔥
Home-page: https://github.com/sidarth16/solderx
Author: Sidarth S
Author-email: Sidarth S <ssidarth1999@gmail.com>
License: MIT
Project-URL: Homepage, https://github.com/sidarth16/solderx
Keywords: solidity,flattener,smart-contracts,cli,etherscan,imports
Classifier: Programming Language :: Python :: 3
Classifier: License :: OSI Approved :: MIT License
Classifier: Operating System :: OS Independent
Classifier: Topic :: Software Development :: Build Tools
Classifier: Topic :: Utilities
Classifier: Intended Audience :: Developers
Requires-Python: >=3.8
License-File: LICENSE
Requires-Dist: requests<3.0.0,>=2.28.0
Requires-Dist: toml
Dynamic: author
Dynamic: home-page
Dynamic: license-file
Dynamic: requires-python
